<layout>
      <configItem>
        <name>ng</name>
        <shortDescription>Nig</shortDescription>
	<description>Nigeria</description>
        <languageList><iso639Id>eng</iso639Id></languageList>
      </configItem>
      <variantList>
        <variant>
          <configItem>
            <name>igbo</name>
            <description>Igbo</description>
            <languageList><iso639Id>ibo</iso639Id></languageList>
          </configItem>
        </variant>
        <variant>
          <configItem>
            <name>yoruba</name>
            <description>Yoruba</description>
            <languageList><iso639Id>yor</iso639Id></languageList>
          </configItem>
        </variant>
        <variant>
          <configItem>
            <name>hausa</name>
            <description>Hausa</description>
            <languageList><iso639Id>hau</iso639Id></languageList>
          </configItem>
        </variant>
	<variant>
          <configItem>
            <name>edo</name>
            <description>Edo</description>
            <languageList><iso639Id>edo</iso639Id></languageList>
          </configItem>
        </variant>
	<variant>
          <configItem>
            <name>gbe</name>
            <description>Phla-Pherá</description>
            <languageList><iso639Id>Phla-Pherá</iso639Id></languageList>
          </configItem>
        </variant>
	<variant>
          <configItem>
            <name>fulfulde</name>
            <description>Fulfulde</description>
            <languageList><iso639Id>ful</iso639Id></languageList>
          </configItem>
        </variant>
	<variant>
          <configItem>
            <name>generic</name>
            <description>Multilingual</description>
            <languageList><iso639Id>Multilingual</iso639Id></languageList>
          </configItem>
        </variant>
      </variantList>
    </layout>

